<theme>
  <formatVersion>7</formatVersion>
  <include>./../theme.xml</include>

  <view name="basic, detailed, video, grid">
    <text name="nameLabel" extra="true">
      <text>Atari Jaguar</text>
    </text>
  </view>

  <view name="system">
    <text name="sys_line1" extra="true">
      <text>Atari</text>
    </text>
    <text name="sys_line2" extra="true">
      <text>Jaguar</text>
    </text>
    <text name="shortdescription" extra="true">
      <text>1993 · Consola 64-bit</text>
    </text>
    <text name="longdescription" extra="true">
      <text>Primera consola de 64 bits de la historia y última de Atari. Tenía una gran potencia pero un escaso repertorio de baja calidad que no lo aprovechó</text>
    </text>
  </view>
</theme>